README.rst
setup.cfg
setup.py
table2dicts.py
table2dicts.egg-info/PKG-INFO
table2dicts.egg-info/SOURCES.txt
table2dicts.egg-info/dependency_links.txt
table2dicts.egg-info/requires.txt
table2dicts.egg-info/top_level.txt