Metadata-Version: 1.1
Name: table2dicts
Version: 0.2
Summary: Python module for converting a html table to a list of dictionaries.
Home-page: http://github.com/moagstar/table2dicts/
Author: Daniel Bradburn
Author-email: moagstar@gmail.com
License: MIT
Download-URL: https://github.com/moagstar/table2dicts/tarball/0.2
Platform: UNKNOWN
Classifier: Development Status :: 1 - Planning
Classifier: Intended Audience :: Developers
Classifier: Natural Language :: English
Classifier: License :: OSI Approved :: MIT License
Classifier: Operating System :: OS Independent
Classifier: Programming Language :: Python
Classifier: Programming Language :: Python :: 2
Classifier: Programming Language :: Python :: 2.6
Classifier: Programming Language :: Python :: 2.7
Classifier: Programming Language :: Python :: 3
Classifier: Programming Language :: Python :: 3.3
Classifier: Programming Language :: Python :: 3.4
Classifier: Topic :: Software Development :: Libraries :: Python Modules
